AUTHORS.rst
LICENSE
README.rst
setup.py
msm_we/__init__.py
msm_we/ensembles.py
msm_we/fpt.py
msm_we/msm_we.py
msm_we/nmm.py
msm_we/optimization.py
msm_we/utils.py
msm_we.egg-info/PKG-INFO
msm_we.egg-info/SOURCES.txt
msm_we.egg-info/dependency_links.txt
msm_we.egg-info/entry_points.txt
msm_we.egg-info/not-zip-safe
msm_we.egg-info/requires.txt
msm_we.egg-info/top_level.txt