Metadata-Version: 2.1
Name: msm-we
Version: 0.1.15
Summary: Code for Markov state modeling of weighted ensemble trajectories.
Home-page: https://github.com/jdrusso/msm_we
Author: John Russo
Author-email: russojd@ohsu.edu
License: MIT license
Keywords: msm_we
Platform: UNKNOWN
Classifier: Development Status :: 2 - Pre-Alpha
Classifier: Intended Audience :: Developers
Classifier: License :: OSI Approved :: MIT License
Classifier: Natural Language :: English
Classifier: Programming Language :: Python :: 3
Classifier: Programming Language :: Python :: 3.5
Classifier: Programming Language :: Python :: 3.6
Classifier: Programming Language :: Python :: 3.7
Classifier: Programming Language :: Python :: 3.8
Requires-Python: >=3.5
Provides-Extra: tests
License-File: LICENSE
License-File: AUTHORS.rst
